{
    "name": "RainMachine",
    "docs": "https://github.com/VE7GEL/RainMachine",
    "type": "python3",
    "executable": "rainmachine.py",
    "install": "install.sh",
    "description": "Rainmachine Node Server for the ISY994",
    "notice": "Only fully tested on Mini-8, some simulation testing for HW version 1",
    "shortPoll": "30",
    "longPoll": "60",
    "testMode": false,
    "profile_version": "1.0.6",
    "credits": [
        {
            "title": "RainMachine: a NodeServer for Green Electronics' Rainmachine Irrigation Controller",
            "author": "Gordon Larsen",
            "version": "0.2.6",
            "date": "February 10, 2020",
            "source": "https://github.com/ve7gel/RainMachine",
            "license": "https://github.com/ve7gel/RainMachine/blob/master/LICENSE"
        }
    ]
}
